jupyterlab_tpt/__init__.py
jupyterlab_tpt/_version.py
jupyterlab_tpt-0.8.1.data/data/share/jupyter/labextensions/jupyterlab-tpt/build_log.json
jupyterlab_tpt-0.8.1.data/data/share/jupyter/labextensions/jupyterlab-tpt/package.json
jupyterlab_tpt-0.8.1.data/data/share/jupyter/labextensions/jupyterlab-tpt/schemas/jupyterlab-tpt/package.json.orig
jupyterlab_tpt-0.8.1.data/data/share/jupyter/labextensions/jupyterlab-tpt/schemas/jupyterlab-tpt/plugin.json
jupyterlab_tpt-0.8.1.data/data/share/jupyter/labextensions/jupyterlab-tpt/static/lib_index_js.0009a08f722eea530ae5.js
jupyterlab_tpt-0.8.1.data/data/share/jupyter/labextensions/jupyterlab-tpt/static/lib_index_js.0009a08f722eea530ae5.js.map
jupyterlab_tpt-0.8.1.data/data/share/jupyter/labextensions/jupyterlab-tpt/static/lib_index_js.03aaec581826f0287335.js
jupyterlab_tpt-0.8.1.data/data/share/jupyter/labextensions/jupyterlab-tpt/static/lib_index_js.03aaec581826f0287335.js.map
jupyterlab_tpt-0.8.1.data/data/share/jupyter/labextensions/jupyterlab-tpt/static/lib_index_js.07236439b2ffe2f690e0.js
jupyterlab_tpt-0.8.1.data/data/share/jupyter/labextensions/jupyterlab-tpt/static/lib_index_js.07236439b2ffe2f690e0.js.map
jupyterlab_tpt-0.8.1.data/data/share/jupyter/labextensions/jupyterlab-tpt/static/lib_index_js.09e47d9ef4a193563383.js
jupyterlab_tpt-0.8.1.data/data/share/jupyter/labextensions/jupyterlab-tpt/static/lib_index_js.09e47d9ef4a193563383.js.map
jupyterlab_tpt-0.8.1.data/data/share/jupyter/labextensions/jupyterlab-tpt/static/lib_index_js.1b816c6c8127be1e7392.js
jupyterlab_tpt-0.8.1.data/data/share/jupyter/labextensions/jupyterlab-tpt/static/lib_index_js.1b816c6c8127be1e7392.js.map
jupyterlab_tpt-0.8.1.data/data/share/jupyter/labextensions/jupyterlab-tpt/static/lib_index_js.1e47496410d8231287bd.js
jupyterlab_tpt-0.8.1.data/data/share/jupyter/labextensions/jupyterlab-tpt/static/lib_index_js.1e47496410d8231287bd.js.map
jupyterlab_tpt-0.8.1.dist-info/METADATA
jupyterlab_tpt-0.8.1.dist-info/WHEEL
jupyterlab_tpt-0.8.1.dist-info/licenses/LICENSE
jupyterlab_tpt-0.8.1.dist-info/RECORD
