Metadata-Version: 2.3
Name: jupyterlab_tpt
Version: 0.8.1
Dynamic: Keywords
Summary: My custom tweaks for using JLAB
Project-URL: Homepage, https://github.com/parmentelat/jupyterlab-tpt
Project-URL: Bug Tracker, https://github.com/parmentelat/jupyterlab-tpt/issues
Project-URL: Repository, https://github.com/parmentelat/jupyterlab-tpt.git
Author-email: Thierry Parmentelat <thierry.parmentelat@inria.fr>
License: BSD 3-Clause License
License-File: LICENSE
Classifier: Framework :: Jupyter
Classifier: Framework :: Jupyter :: JupyterLab
Classifier: Framework :: Jupyter :: JupyterLab :: 4
Classifier: Framework :: Jupyter :: JupyterLab :: Extensions
Classifier: Framework :: Jupyter :: JupyterLab :: Extensions :: Prebuilt
Classifier: License :: OSI Approved :: BSD License
Classifier: Programming Language :: Python
Classifier: Programming Language :: Python :: 3
Classifier: Programming Language :: Python :: 3.8
Classifier: Programming Language :: Python :: 3.9
Classifier: Programming Language :: Python :: 3.10
Classifier: Programming Language :: Python :: 3.11
Requires-Python: >=3.8
Requires-Dist: jupyterlab-courselevels
Requires-Dist: jupyterlab-gridwidth
Requires-Dist: jupyterlab-hidecell
